{"data":{"21111111":{"name":"AAA","lastName":"AAAA","cpr":"1234512345","email":"a@a.com","active":1,"activationKey":"5c6dc9fed6ab1","password":"$2y$10$tMzUFlF6LB0QmCFOsRpHiOMM7aJ711339dUgH6cigONjV\/p66oQ8y","balance":111,"transactions":{"5c6eaba845af4":{"date":1550756776,"amount":"11","firstName":"Name that I hardcoded","lastName":"Lastname that I hardcoded","fromPhone":"21111111","message":"sdd"}},"transactionsNotRead":{"5c6eaba845af4":{"date":1550756776,"amount":"11","firstName":"Name that I hardcoded","lastName":"Lastname that I hardcoded","fromPhone":"21111111","message":"sdd"}},"accounts":{"5c6dc9fee6368":{"balance":0}}},"21222222":{"name":"BBB","lastName":"BBBB","cpr":"3482749334","email":"b@B.com","active":1,"activationKey":"5c6dca27cdc86","password":"$2y$10$hY.MiHLBf4tsx\/FtU9XL3u531kNluBXi33RMQb5aiZIzNU9jyqjg2","balance":0,"transactions":{},"transactionsNotRead":{},"accounts":{"5c6dca27dd31c":{"balance":0}}},"21333333":{"name":"CCC","lastName":"CCCC","cpr":"9845362748","email":"c@c.com","active":1,"activationKey":"5c6dca428d0e0","password":"$2y$10$ybEXsrZQdc6bdCtaWVApieGjMuYK19JqmmpfmJ\/EgwHLKkXJLtkBa","balance":0,"transactions":{},"transactionsNotRead":{},"accounts":{"5c6dca429c687":{"balance":0}}},"21444444":{"firstName":"BBB","lastName":"OKAFOR","cpr":"1234512345","email":"a@a.com","active":1,"activationKey":"5c6e717e2fd8d","password":"$2y$10$MnWCLI52ItxdC9P66gM5Bei\/xgeqNT4yJrmtpcGTMzevYedNlTKP.","transactions":{},"transactionsNotRead":{},"accounts":{"5c6e717e3f1fb":{"balance":0}}},"21999999":{"firstName":"QQQ","lastName":"QQQQ","cpr":"1234123456","email":"Q@q.com","active":1,"activationKey":"5c6e88ede78c3","password":"$2y$10$ecRr2\/09LL1HRB0Rr82GSuZKoELJUXqitqXENJLUz.kFueXPVsEvO","transactions":{},"transactionsNotRead":{},"accounts":{"5c6e88ee04278":{"balance":0}}},"21888888":{"firstName":"WWW","lastName":"WWWW","cpr":"1234123456","email":"w@w.com","balance":100,"active":1,"activationKey":"5c6e89c0808cb","password":"$2y$10$QkdPTrqrmZ6\/I4Q\/xxsuW.7YiX9uSeZJObXnJ4Qtigq\/WnRbApb7a","transactions":{},"transactionsNotRead":{},"accounts":{"5c6e89c091ba9":{"balance":0}}}}}